dal_pdf_creator/__init__.py
dal_pdf_creator/creator.py
dal_pdf_creator/example/__init__.py
dal_pdf_creator/example/book.py
dal_pdf_creator-0.0.3.dist-info/LICENSE
dal_pdf_creator-0.0.3.dist-info/METADATA
dal_pdf_creator-0.0.3.dist-info/WHEEL
dal_pdf_creator-0.0.3.dist-info/top_level.txt
dal_pdf_creator-0.0.3.dist-info/RECORD
